trades/__init__.py
trades/__main__.py
trade_log-1.3.0.dist-info/LICENSE
trade_log-1.3.0.dist-info/METADATA
trade_log-1.3.0.dist-info/WHEEL
trade_log-1.3.0.dist-info/entry_points.txt
trade_log-1.3.0.dist-info/top_level.txt
trade_log-1.3.0.dist-info/RECORD
